demos/__init__.py
demos/repeated_timer_demo.py
demos/time_string_demo.py
general_util/__init__.py
general_util/file.py
general_util/repeated_timer.py
general_util/time_string.py
general_util-1.0.1.dist-info/LICENSE
general_util-1.0.1.dist-info/METADATA
general_util-1.0.1.dist-info/WHEEL
general_util-1.0.1.dist-info/top_level.txt
general_util-1.0.1.dist-info/RECORD
