Metadata-Version: 2.1
Name: general-util
Version: 1.0.1
Summary: General utilities for python scripts.
Author: John Halazonetis
Author-email: <john.halazonetis@icloud.com>
Project-URL: Documentation, https://johnhal.gitlab.io/util_python
Project-URL: Repository, https://gitlab.com/johnhal/util_python
Keywords: python,utilities
Classifier: Intended Audience :: Developers
Classifier: Programming Language :: Python :: 3
Classifier: Operating System :: Unix
Classifier: Operating System :: MacOS :: MacOS X
Classifier: Operating System :: Microsoft :: Windows
License-File: LICENSE
Requires-Dist: pathlib
